online_store/__init__.py
online_store/__main__.py
online_store/order_management.py
online_store/user_management.py
chickens_polish-0.1.0.dist-info/METADATA
chickens_polish-0.1.0.dist-info/WHEEL
chickens_polish-0.1.0.dist-info/top_level.txt
chickens_polish-0.1.0.dist-info/RECORD
