Metadata-Version: 2.1
Name: chickens-polish
Version: 0.1.0
Summary: Исполняемый пакет для управления пользователями и заказами в онлайн-магазине
Author-email: Semyon Drozdov <s.drozdov@edu.centraluniversity.ru>
License: MIT
Requires-Python: >=3.8
